LICENSE
MANIFEST.in
README.md
README.rst
setup.py
test/__init__.py
test/datasets/__init__.py
test/datasets/test_basic.py
test/datasets/test_emotion_recognition.py
test/datasets/test_motor_imagery.py
test/datasets/test_personal_identification.py
test/datasets/test_sleep_stage_detection.py
test/datasets/test_ssvep.py
test/io/__init__.py
test/io/test_eeg_signal.py
test/io/test_meta_info.py
test/model_selection/__init__.py
test/model_selection/test_k_fold.py
test/model_selection/test_leave_one_subject_out.py
test/model_selection/test_per_subject.py
test/model_selection/test_split.py
test/models/__init__.py
test/models/test_cnn.py
test/models/test_ddpm.py
test/models/test_flow.py
test/models/test_gan.py
test/models/test_gnn.py
test/models/test_rnn.py
test/models/test_transformer.py
test/models/test_vae.py
test/trainers/__init__.py
test/trainers/test_basic_trainer.py
test/trainers/test_ddpm_trainer.py
test/trainers/test_domain_adaption_trainer.py
test/trainers/test_gan_trainer.py
test/trainers/test_glow_trainer.py
test/trainers/test_imbalance_trainer.py
test/trainers/test_self_supervised_trainer.py
test/trainers/test_vae_trainer.py
test/transforms/__init__.py
test/transforms/test_any.py
test/transforms/test_hooks.py
test/transforms/test_label.py
test/transforms/test_numpy.py
test/transforms/test_pyg.py
test/transforms/test_torch.py
test/utils/__init__.py
test/utils/test_visualize.py
torcheeg/__init__.py
torcheeg.egg-info/PKG-INFO
torcheeg.egg-info/SOURCES.txt
torcheeg.egg-info/dependency_links.txt
torcheeg.egg-info/requires.txt
torcheeg.egg-info/top_level.txt
torcheeg/datasets/__init__.py
torcheeg/datasets/constants/__init__.py
torcheeg/datasets/constants/region_1020.py
torcheeg/datasets/constants/standard_1005.py
torcheeg/datasets/constants/standard_1020.py
torcheeg/datasets/constants/utils.py
torcheeg/datasets/constants/clinical/__init__.py
torcheeg/datasets/constants/clinical/tuh_tueg.py
torcheeg/datasets/constants/emotion_recognition/__init__.py
torcheeg/datasets/constants/emotion_recognition/amigos.py
torcheeg/datasets/constants/emotion_recognition/bci2022.py
torcheeg/datasets/constants/emotion_recognition/deap.py
