Metadata-Version: 2.1
Name: torcheeg
Version: 1.1.3
Summary: TorchEEG is a library built on PyTorch for EEG signal analysis. TorchEEG aims to provide a plug-and-play EEG analysis tool, so that researchers can quickly reproduce EEG analysis work and start new EEG analysis research without paying attention to technical details unrelated to the research focus.
Home-page: https://github.com/tczhangzhi/torcheeg
Author: TorchEEG Team
Author-email: tczhangzhi@gmail.com
License: MIT
Keywords: PyTorch,EEG
Requires-Python: >=3.7
Provides-Extra: example
Provides-Extra: test
Provides-Extra: pyg
Provides-Extra: moabb
License-File: LICENSE
